vcfy/__init__.py
vcfy/cli.py
vcfy/ksnper.py
vcfy/model.py
vcfy/release.py
vcfy/util.py
vcfy/resources/__init__.py
vcfy/resources/templates/__init__.py
vcfy/resources/templates/template.vcf
vcfy-0.0.9.dist-info/LICENSE
vcfy-0.0.9.dist-info/METADATA
vcfy-0.0.9.dist-info/WHEEL
vcfy-0.0.9.dist-info/entry_points.txt
vcfy-0.0.9.dist-info/top_level.txt
vcfy-0.0.9.dist-info/RECORD
