Metadata-Version: 2.1
Name: vcfy
Version: 0.0.9
Summary: Generate VCF file with random variants from reference genome
Home-page: https://github.com/cartoonist/vcfy
Author: Ali Ghaffaari
Author-email: ali.ghaffaari@mpi-inf.mpg.de
License: MIT
Download-URL: https://github.com/cartoonist/vcfy/tarball/0.0.9
Keywords: vcf genome genomics variation DNA sequence ngs
Platform: UNKNOWN
Classifier: Development Status :: 2 - Pre-Alpha
Classifier: Environment :: Console
Classifier: License :: OSI Approved :: MIT License
Classifier: Programming Language :: Python :: 3
Classifier: Programming Language :: Python :: 3.6
Classifier: Programming Language :: Python :: 3.7
Classifier: Programming Language :: Python :: 3.8
Classifier: Programming Language :: Python :: 3.9
Classifier: Intended Audience :: Science/Research
Classifier: Topic :: Scientific/Engineering :: Bio-Informatics
Requires-Dist: PyVCF (>=0.6.8)
Requires-Dist: biopython (>=1.71)
Requires-Dist: numpy (>=1.14.3)
Requires-Dist: BitVector (>=3.4.8)
Requires-Dist: click (>=6.7)
Provides-Extra: test
Requires-Dist: nose (>=1.0) ; extra == 'test'
Requires-Dist: coverage ; extra == 'test'
